{
    "resultCount": 3,
    "res":    [
                   {
                   "artistName": "Name1",
                   "trackName": "Track1",
                   "artworkUrl60": "ImageURL1",
                   "someOtherField": 6.99
                   
                   },
                   {
                   
                   "artistName": "Name2",
                   "trackName": "Track2",
                   "artworkUrl60": "ImageURL2",
                   "someOtherField": "Rock"
                   },
                   {
                   
                   "artistName": "Name3",
                   "trackName": "Track3",
                   "artworkUrl60": "ImageURL3",
                   "someOtherField": "Rock"
                   }
                   ]
}
